flet_mvp_utils/__init__.py
flet_mvp_utils/datasource.py
flet_mvp_utils/error.py
flet_mvp_utils/model.py
flet_mvp_utils/observable.py
flet_mvp_utils/presenter.py
flet_mvp_utils/protocols.py
flet_mvp_utils/view.py
flet_mvp_utils-0.4.1.dist-info/METADATA
flet_mvp_utils-0.4.1.dist-info/WHEEL
flet_mvp_utils-0.4.1.dist-info/LICENSE
flet_mvp_utils-0.4.1.dist-info/RECORD
