Metadata-Version: 2.1
Name: flet-mvp-utils
Version: 0.4.1
Summary: Tools to build flet apps with the MVP architecture pattern
License: Apache-2.0
Author: iron3oxide
Author-email: jason.hottelet@tuta.io
Requires-Python: >=3.10,<4.0
Classifier: License :: OSI Approved :: Apache Software License
Classifier: Programming Language :: Python :: 3
Classifier: Programming Language :: Python :: 3.10
Classifier: Programming Language :: Python :: 3.11
Requires-Dist: abstractcp (>=0.9.9,<0.10.0)
Requires-Dist: flet (>=0.4.0,<0.5.0)
Requires-Dist: flet-routed-app (>=0.3.3,<0.4.0)
Requires-Dist: pydantic (>=1.10.4,<2.0.0)
